ultradetector/__init__.py
ultradetector/python_api.py
ultradetector/ultralytics/__init__.py
ultradetector/ultralytics/cfg/__init__.py
ultradetector/ultralytics/data/__init__.py
ultradetector/ultralytics/data/annotator.py
ultradetector/ultralytics/data/augment.py
ultradetector/ultralytics/data/base.py
ultradetector/ultralytics/data/build.py
ultradetector/ultralytics/data/converter.py
ultradetector/ultralytics/data/dataset.py
ultradetector/ultralytics/data/loaders.py
ultradetector/ultralytics/data/split_dota.py
ultradetector/ultralytics/data/utils.py
ultradetector/ultralytics/engine/__init__.py
ultradetector/ultralytics/engine/exporter.py
ultradetector/ultralytics/engine/model.py
ultradetector/ultralytics/engine/predictor.py
ultradetector/ultralytics/engine/results.py
ultradetector/ultralytics/engine/trainer.py
ultradetector/ultralytics/engine/tuner.py
ultradetector/ultralytics/engine/validator.py
ultradetector/ultralytics/hub/__init__.py
ultradetector/ultralytics/hub/auth.py
ultradetector/ultralytics/hub/session.py
ultradetector/ultralytics/hub/utils.py
ultradetector/ultralytics/hub/google/__init__.py
ultradetector/ultralytics/models/__init__.py
ultradetector/ultralytics/models/fastsam/__init__.py
ultradetector/ultralytics/models/fastsam/model.py
ultradetector/ultralytics/models/fastsam/predict.py
ultradetector/ultralytics/models/fastsam/utils.py
ultradetector/ultralytics/models/fastsam/val.py
ultradetector/ultralytics/models/nas/__init__.py
ultradetector/ultralytics/models/nas/model.py
ultradetector/ultralytics/models/nas/predict.py
ultradetector/ultralytics/models/nas/val.py
ultradetector/ultralytics/models/rtdetr/__init__.py
ultradetector/ultralytics/models/rtdetr/model.py
ultradetector/ultralytics/models/rtdetr/predict.py
ultradetector/ultralytics/models/rtdetr/train.py
ultradetector/ultralytics/models/rtdetr/val.py
ultradetector/ultralytics/models/sam/__init__.py
ultradetector/ultralytics/models/sam/amg.py
ultradetector/ultralytics/models/sam/build.py
ultradetector-0.2.2.dist-info/METADATA
ultradetector-0.2.2.dist-info/WHEEL
ultradetector-0.2.2.dist-info/entry_points.txt
ultradetector-0.2.2.dist-info/top_level.txt
ultradetector-0.2.2.dist-info/RECORD
