Metadata-Version: 2.4
Name: ultradetector
Version: 0.2.2
Author: weki
Classifier: Programming Language :: Python :: 3.10
Classifier: License :: OSI Approved :: MIT License
Requires-Python: >=3.8
Requires-Dist: numpy
Requires-Dist: nibabel
Requires-Dist: matplotlib
Requires-Dist: opencv-python
Requires-Dist: psutil
Requires-Dist: pyyaml
Requires-Dist: requests
Requires-Dist: ultralytics
Dynamic: author
Dynamic: classifier
Dynamic: requires-dist
Dynamic: requires-python
